[
  {
    "ServiceHeaderBlockId": 1,
    "ServiceHeaderBlockTitle": "Header",
    "NodeText": "/",
    "NodeLevel": 0,
    "IsServiceBlock": false,
    "ResourceDescriptionId": null,
    "IsActive": true,
    "children": [
      {
        "ServiceHeaderBlockId": 57,
        "ServiceHeaderBlockTitle": "Project Administration",
        "NodeText": "/1/",
        "NodeLevel": 1,
        "IsServiceBlock": false,
        "ResourceDescriptionId": null,
        "IsActive": true
      },
      {
        "ServiceHeaderBlockId": 58,
        "ServiceHeaderBlockTitle": "Innovation",
        "NodeText": "/2/",
        "NodeLevel": 1,
        "IsServiceBlock": false,
        "ResourceDescriptionId": null,
        "IsActive": true
      },
      {
        "ServiceHeaderBlockId": 76,
        "ServiceHeaderBlockTitle": "Commercialization",
        "NodeText": "/3/",
        "NodeLevel": 1,
        "IsServiceBlock": false,
        "ResourceDescriptionId": null,
        "IsActive": true,
        "children": [
          {
            "ServiceHeaderBlockId": 78,
            "ServiceHeaderBlockTitle": "Co-Man sourcing",
            "NodeText": "/3/1/",
            "NodeLevel": 2,
            "IsServiceBlock": false,
            "ResourceDescriptionId": null,
            "IsActive": true
          }
        ]
      }
    ]
  }
]
